magicinpaint_gpu-1.0.2.data/purelib/magicinpaint.pyd
magicinpaint_gpu-1.0.2.dist-info/LICENSE
magicinpaint_gpu-1.0.2.dist-info/METADATA
magicinpaint_gpu-1.0.2.dist-info/WHEEL
magicinpaint_gpu-1.0.2.dist-info/top_level.txt
magicinpaint_gpu-1.0.2.dist-info/RECORD
