Metadata-Version: 2.1
Name: magicinpaint-gpu
Version: 1.0.2
Summary: Image Inpaint Library
Author: Anton Milev
Author-email: amil@abv.bg
License-File: LICENSE
